xasyncio/__init__.py
xasyncio/queue.py
xasyncio/utils.py
xasyncio-0.2.12.dist-info/METADATA
xasyncio-0.2.12.dist-info/WHEEL
xasyncio-0.2.12.dist-info/licenses/LICENSE
xasyncio-0.2.12.dist-info/RECORD
