Metadata-Version: 2.4
Name: xasyncio
Version: 0.2.12
Summary: A package to simiplify multithreaded asyncio event loops
Project-URL: Homepage, https://github.com/shawn-peng/xasyncio
Project-URL: Bug Tracker, https://github.com/shawn-peng/xasyncio/issues
Author-email: Yisu Peng <yisupeng@gmail.com>
License-File: LICENSE
Classifier: License :: OSI Approved :: MIT License
Classifier: Operating System :: OS Independent
Classifier: Programming Language :: Python :: 3
Requires-Python: >=3.7
